{
    "features": [
        {
            "geometry": {
                "coordinates": [
                    77.638635414, 
                    12.959526308
                ], 
                "type": "Point"
            }, 
            "properties": {
                "ADDRESS": "7th Cross Road, Domlur I Stage, Domlur, Bangalore, Karnataka 560071, India", 
                "CAPTION": "Dommalur #openpostboxindia", 
                "CONTRIBUTOR": "instagram-thejeshgn", 
                "DISTRICT": "Bangalore", 
                "HOMEPAGE": "http://openbangalore.org/postbox/pb/id/401915144801695310_31979172", 
                "ID": "401915144801695310_31979172", 
                "IMG": "http://distilleryimage2.s3.amazonaws.com/dfaa4e6a825611e2be8622000a9f192b_7.jpg", 
                "PINCODE": "560071", 
                "STATE": "Karnataka", 
                "TAGS": "openpostboxindia"
            }, 
            "type": "Feature"
        }, 
        {
            "geometry": {
                "coordinates": [
                    77.636024472, 
                    12.960954639
                ], 
                "type": "Point"
            }, 
            "properties": {
                "ADDRESS": "5, Service Road, 1st Stage, Domlur, Bangalore, Karnataka 560071, India", 
                "CAPTION": "Near Ashoka Domlur #openpostboxindia #pin560071", 
                "CONTRIBUTOR": "instagram-anjananju", 
                "DISTRICT": "Bangalore Urban", 
                "HOMEPAGE": "http://openbangalore.org/postbox/pb/id/654061701467309278_582942400", 
                "ID": "654061701467309278_582942400", 
                "IMG": "http://distilleryimage1.s3.amazonaws.com/8144722e93b711e3a6e5120b07343bd9_8.jpg", 
                "PINCODE": "560071", 
                "STATE": "Karnataka", 
                "TAGS": "openpostboxindia, pin560071"
            }, 
            "type": "Feature"
        }
    ], 
    "type": "FeatureCollection"
}