{
    "features": [
        {
            "geometry": {
                "coordinates": [
                    77.228811604, 
                    28.660669325
                ], 
                "type": "Point"
            }, 
            "properties": {
                "ADDRESS": "Shyama Prasad Mukherji Marg, New Delhi, Delhi 110006, India", 
                "CAPTION": "Delhi railway station", 
                "CONTRIBUTOR": "instagram-thejeshgn", 
                "DISTRICT": "North Delhi", 
                "HOMEPAGE": "http://openbangalore.org/postbox/pb/id/386779241670325331_31979172", 
                "ID": "386779241670325331_31979172", 
                "IMG": "http://distilleryimage11.s3.amazonaws.com/d111632671ed11e2b55122000a1f9be7_7.jpg", 
                "PINCODE": "110006", 
                "STATE": "Delhi", 
                "TAGS": "openpostboxindia"
            }, 
            "type": "Feature"
        }
    ], 
    "type": "FeatureCollection"
}