{
    "features": [
        {
            "geometry": {
                "coordinates": [
                    77.6926091, 
                    12.8144984
                ], 
                "type": "Point"
            }, 
            "properties": {
                "ADDRESS": "Hosur Road, Bommasandra Industrial Area, Electronics City, Bangalore, Karnataka, India", 
                "CAPTION": "In front of Narayana Hrudayalaya Hospital", 
                "CONTRIBUTOR": "instagram-thejeshgn", 
                "DISTRICT": "Bengaluru Urban", 
                "HOMEPAGE": "http://openbangalore.org/postbox/pb/id/372135278942435076_31979172", 
                "ID": "372135278942435076_31979172", 
                "IMG": "http://distilleryimage0.s3.amazonaws.com/4cef1970620d11e28a2c22000a9f15d9_7.jpg", 
                "PINCODE": "560099", 
                "STATE": "Karnataka", 
                "TAGS": "openpostboxindia, pin560099"
            }, 
            "type": "Feature"
        }, 
        {
            "geometry": {
                "coordinates": [
                    77.6885533, 
                    12.8194804
                ], 
                "type": "Point"
            }, 
            "properties": {
                "ADDRESS": "Bommasandra Industrial Area, Electronics City, Bangalore, Karnataka, India", 
                "CAPTION": "Bommasandra Industrial Estate Post Office.", 
                "CONTRIBUTOR": "instagram-thejeshgn", 
                "DISTRICT": "Bengaluru Urban", 
                "HOMEPAGE": "http://openbangalore.org/postbox/pb/id/372142370680026935_31979172", 
                "ID": "372142370680026935_31979172", 
                "IMG": "http://distilleryimage11.s3.amazonaws.com/44d4788c620f11e289dc22000a9f12b0_7.jpg", 
                "PINCODE": "560099", 
                "STATE": "Karnataka", 
                "TAGS": "openpostboxindia, pin560099, postoffice"
            }, 
            "type": "Feature"
        }
    ], 
    "type": "FeatureCollection"
}